{
  "data": [
    {
      "id": "xx",
      "name": "xxx",
      "description": "xxxxx",
      "activities": [
        {
          "id": "xxx",
          "name": "xxx",
          "description": "xxxx",
          "tasks": [
            {
              "id": "yyy",
              "name": "xxx",
              "description": ""
            }
          ]
        },
        {
          "id": "yyy",
          "name": "xxx",
          "description": "xxxx",
          "tasks": [
            {
              "id": "yyy",
              "name": "xxx",
              "description": ""
            }
          ]
        }
      ]
    }
  ]
}